autotrace/__init__.py
autotrace/__main__.py
autotrace/_autotrace.c
autotrace/_autotrace.cp313-win_amd64.pyd
autotrace/_autotrace.pxd
autotrace/_autotrace.pyx
autotrace/autotrace.py
autotrace/overrides.cpp
autotrace/py.typed
pyautotrace-0.0.7.dist-info/licenses/LICENSE-autotrace.txt
pyautotrace-0.0.7.dist-info/licenses/LICENSE.txt
pyautotrace-0.0.7.dist-info/METADATA
pyautotrace-0.0.7.dist-info/WHEEL
pyautotrace-0.0.7.dist-info/entry_points.txt
pyautotrace-0.0.7.dist-info/top_level.txt
pyautotrace-0.0.7.dist-info/RECORD
