Metadata-Version: 2.4
Name: pyautotrace
Version: 0.0.7
Summary: Python bindings for AutoTrace.
Author-email: Lemonyte <contact@lemonyte.com>
License-Expression: LGPL-2.1-or-later
Project-URL: Repository, https://github.com/lemonyte/pyautotrace
Keywords: autotrace,bitmap,graphics,tracing,vector
Classifier: Development Status :: 3 - Alpha
Classifier: Intended Audience :: Developers
Classifier: Operating System :: OS Independent
Classifier: Programming Language :: Cython
Classifier: Programming Language :: Python :: 3
Classifier: Topic :: Multimedia :: Graphics :: Graphics Conversion
Classifier: Topic :: Scientific/Engineering :: Image Processing
Classifier: Typing :: Typed
Requires-Python: >=3.10
License-File: LICENSE.txt
License-File: LICENSE-autotrace.txt
Dynamic: license-file
